Workbook

Sheet Instructions
A1: Highglen Plastic Industries — Stock & Cash Control Workbook
A3: How this workbook is organised:
A4: 1. Material Intake — Crushing Office logs every purchase/delivery of PP, HD or LD material from buyers.
A5: 2. Crushing Production — Crusher operator logs input material vs output chips and the processing loss.
A6: 3. Dispatch to Palletizing — Crushing Office logs each batch of chips sent to the Palletizing Office.
A7: 4. Palletizing Receipt — Palletizing Office logs chips received and the $/kg amount payable to the Crushing Office.
A8: 5. Palletizing Production — Machine operators log chips input vs pellets output and the processing loss.
A9: 6. Pellet Sales — Supervisor logs each cash sale of finished pellets to the market.
A10: 7. Cash Remittance — Supervisor logs cash remitted back to the Crushing Office (capped at kg delivered x recovery price) and the balance retained.
A11: 8. Dashboard — automatically summarises stock movements, processing losses and the cash reconciliation between the two offices.
A13: Colour key:
A14: Blue text on a white background = type your data here.
... A19: The Dashboard sheet updates automatically as you add rows — no manual totalling required.

Sheet 1. Material Intake
A1: 1. Material Intake — Crushing Office
A2: Every purchase of PP / HD / LD material delivered by buyers
A3: Date | B3: GRN No. | C3: Buyer name | D3: Material type (PP/HD/LD) | E3: Gross weight (kg) | F3: Tare weight (kg) | G3: Net weight (kg) | H3: Unit price ($/kg) | I3: Total value ($) | J3: Received by
A4: 2026-07-01 | B4: GRN-CR-0001 | C4: Tendai Moyo | D4: PP | E4: 520 | F4: 20 | G4: =IF(AND(E4<>"",F4<>""),E4-F4,"") -> 500 | H4: 0.35 | I4: =IF(AND(G4<>"",H4<>""),G4*H4,"") -> 175 | J4: S. Ncube
G5: =IF(AND(E5<>"",F5<>""),E5-F5,"") | I5: =IF(AND(G5<>"",H5<>""),G5*H5,"")
G6: =IF(AND(E6<>"",F6<>""),E6-F6,"") | I6: =IF(AND(G6<>"",H6<>""),G6*H6,"")
G7: =IF(AND(E7<>"",F7<>""),E7-F7,"") | I7: =IF(AND(G7<>"",H7<>""),G7*H7,"")
G8: =IF(AND(E8<>"",F8<>""),E8-F8,"") | I8: =IF(AND(G8<>"",H8<>""),G8*H8,"")
G9: =IF(AND(E9<>"",F9<>""),E9-F9,"") | I9: =IF(AND(G9<>"",H9<>""),G9*H9,"")
G10: =IF(AND(E10<>"",F10<>""),E10-F10,"") | I10: =IF(AND(G10<>"",H10<>""),G10*H10,"")
G11: =IF(AND(E11<>"",F11<>""),E11-F11,"") | I11: =IF(AND(G11<>"",H11<>""),G11*H11,"")
G12: =IF(AND(E12<>"",F12<>""),E12-F12,"") | I12: =IF(AND(G12<>"",H12<>""),G12*H12,"")
G13: =IF(AND(E13<>"",F13<>""),E13-F13,"") | I13: =IF(AND(G13<>"",H13<>""),G13*H13,"")
G14: =IF(AND(E14<>"",F14<>""),E14-F14,"") | I14: =IF(AND(G14<>"",H14<>""),G14*H14,"")
G15: =IF(AND(E15<>"",F15<>""),E15-F15,"") | I15: =IF(AND(G15<>"",H15<>""),G15*H15,"")
G16: =IF(AND(E16<>"",F16<>""),E16-F16,"") | I16: =IF(AND(G16<>"",H16<>""),G16*H16,"")
... G203: =IF(AND(E203<>"",F203<>""),E203-F203,"") | I203: =IF(AND(G203<>"",H203<>""),G203*H203,"")

Sheet 2. Crushing Production
A1: 2. Crushing Production
A2: Crusher operator's log: material in, plastic chips out
A3: Date | B3: Batch No. | C3: GRN ref(s) | D3: Material type (PP/HD/LD) | E3: Input weight (kg) | F3: Output chips (kg) | G3: Loss (kg) | H3: Loss % | I3: Operator
A4: 2026-07-01 | B4: BC-0001 | C4: GRN-CR-0001 | D4: PP | E4: 520 | F4: 468 | G4: =IF(AND(E4<>"",F4<>""),E4-F4,"") -> 52 | H4: =IF(AND(E4<>"",E4<>0,G4<>""),G4/E4,"") -> 0.1 | I4: T. Chikwanha
G5: =IF(AND(E5<>"",F5<>""),E5-F5,"") | H5: =IF(AND(E5<>"",E5<>0,G5<>""),G5/E5,"")
G6: =IF(AND(E6<>"",F6<>""),E6-F6,"") | H6: =IF(AND(E6<>"",E6<>0,G6<>""),G6/E6,"")
G7: =IF(AND(E7<>"",F7<>""),E7-F7,"") | H7: =IF(AND(E7<>"",E7<>0,G7<>""),G7/E7,"")
G8: =IF(AND(E8<>"",F8<>""),E8-F8,"") | H8: =IF(AND(E8<>"",E8<>0,G8<>""),G8/E8,"")
G9: =IF(AND(E9<>"",F9<>""),E9-F9,"") | H9: =IF(AND(E9<>"",E9<>0,G9<>""),G9/E9,"")
G10: =IF(AND(E10<>"",F10<>""),E10-F10,"") | H10: =IF(AND(E10<>"",E10<>0,G10<>""),G10/E10,"")
G11: =IF(AND(E11<>"",F11<>""),E11-F11,"") | H11: =IF(AND(E11<>"",E11<>0,G11<>""),G11/E11,"")
G12: =IF(AND(E12<>"",F12<>""),E12-F12,"") | H12: =IF(AND(E12<>"",E12<>0,G12<>""),G12/E12,"")
G13: =IF(AND(E13<>"",F13<>""),E13-F13,"") | H13: =IF(AND(E13<>"",E13<>0,G13<>""),G13/E13,"")
G14: =IF(AND(E14<>"",F14<>""),E14-F14,"") | H14: =IF(AND(E14<>"",E14<>0,G14<>""),G14/E14,"")
G15: =IF(AND(E15<>"",F15<>""),E15-F15,"") | H15: =IF(AND(E15<>"",E15<>0,G15<>""),G15/E15,"")
G16: =IF(AND(E16<>"",F16<>""),E16-F16,"") | H16: =IF(AND(E16<>"",E16<>0,G16<>""),G16/E16,"")
... G203: =IF(AND(E203<>"",F203<>""),E203-F203,"") | H203: =IF(AND(E203<>"",E203<>0,G203<>""),G203/E203,"")

Sheet 3. Dispatch to Palletizing
A1: 3. Dispatch to Palletizing Office
A2: Chips sent from the Crushing Office to the Palletizing Office
A3: Date | B3: Dispatch note No. | C3: Batch ref | D3: Material type (PP/HD/LD) | E3: Weight dispatched (kg) | F3: Transported by | G3: Dispatched by
A4: 2026-07-02 | B4: DN-0001 | C4: BC-0001 | D4: PP | E4: 468 | F4: M. Sibanda (truck) | G4: S. Ncube

Sheet 4. Palletizing Receipt
A1: 4. Palletizing Receipt
A2: Chips received at the Palletizing Office; $/kg amount owed to the Crushing Office
A3: Date | B3: GRN No. | C3: Dispatch note ref | D3: Material type (PP/HD/LD) | E3: Weight received (kg) | F3: Rate ($/kg) | G3: Amount payable to Crushing Office ($) | H3: Received by
A4: 2026-07-02 | B4: GRN-PL-0001 | C4: DN-0001 | D4: PP | E4: 465 | F4: 0.1 | G4: =IF(AND(E4<>"",F4<>""),E4*F4,"") -> 46.5 | H4: B. Dube
G5: =IF(AND(E5<>"",F5<>""),E5*F5,"")
G6: =IF(AND(E6<>"",F6<>""),E6*F6,"")
G7: =IF(AND(E7<>"",F7<>""),E7*F7,"")
G8: =IF(AND(E8<>"",F8<>""),E8*F8,"")
G9: =IF(AND(E9<>"",F9<>""),E9*F9,"")
G10: =IF(AND(E10<>"",F10<>""),E10*F10,"")
G11: =IF(AND(E11<>"",F11<>""),E11*F11,"")
G12: =IF(AND(E12<>"",F12<>""),E12*F12,"")
G13: =IF(AND(E13<>"",F13<>""),E13*F13,"")
G14: =IF(AND(E14<>"",F14<>""),E14*F14,"")
G15: =IF(AND(E15<>"",F15<>""),E15*F15,"")
G16: =IF(AND(E16<>"",F16<>""),E16*F16,"")
... G203: =IF(AND(E203<>"",F203<>""),E203*F203,"")

Sheet 5. Palletizing Production
A1: 5. Palletizing Production
A2: Machine operators' log: chips in, finished pellets out
A3: Date | B3: Batch No. | C3: GRN ref | D3: Input chips (kg) | E3: Output pellets (kg) | F3: Loss (kg) | G3: Loss % | H3: Operator
A4: 2026-07-03 | B4: BP-0001 | C4: GRN-PL-0001 | D4: 465 | E4: 430 | F4: =IF(AND(D4<>"",E4<>""),D4-E4,"") -> 35 | G4: =IF(AND(D4<>"",D4<>0,F4<>""),F4/D4,"") -> 0.075268817 | H4: R. Moyana
F5: =IF(AND(D5<>"",E5<>""),D5-E5,"") | G5: =IF(AND(D5<>"",D5<>0,F5<>""),F5/D5,"")
F6: =IF(AND(D6<>"",E6<>""),D6-E6,"") | G6: =IF(AND(D6<>"",D6<>0,F6<>""),F6/D6,"")
F7: =IF(AND(D7<>"",E7<>""),D7-E7,"") | G7: =IF(AND(D7<>"",D7<>0,F7<>""),F7/D7,"")
F8: =IF(AND(D8<>"",E8<>""),D8-E8,"") | G8: =IF(AND(D8<>"",D8<>0,F8<>""),F8/D8,"")
F9: =IF(AND(D9<>"",E9<>""),D9-E9,"") | G9: =IF(AND(D9<>"",D9<>0,F9<>""),F9/D9,"")
F10: =IF(AND(D10<>"",E10<>""),D10-E10,"") | G10: =IF(AND(D10<>"",D10<>0,F10<>""),F10/D10,"")
F11: =IF(AND(D11<>"",E11<>""),D11-E11,"") | G11: =IF(AND(D11<>"",D11<>0,F11<>""),F11/D11,"")
F12: =IF(AND(D12<>"",E12<>""),D12-E12,"") | G12: =IF(AND(D12<>"",D12<>0,F12<>""),F12/D12,"")
F13: =IF(AND(D13<>"",E13<>""),D13-E13,"") | G13: =IF(AND(D13<>"",D13<>0,F13<>""),F13/D13,"")
F14: =IF(AND(D14<>"",E14<>""),D14-E14,"") | G14: =IF(AND(D14<>"",D14<>0,F14<>""),F14/D14,"")
F15: =IF(AND(D15<>"",E15<>""),D15-E15,"") | G15: =IF(AND(D15<>"",D15<>0,F15<>""),F15/D15,"")
F16: =IF(AND(D16<>"",E16<>""),D16-E16,"") | G16: =IF(AND(D16<>"",D16<>0,F16<>""),F16/D16,"")
... F203: =IF(AND(D203<>"",E203<>""),D203-E203,"") | G203: =IF(AND(D203<>"",D203<>0,F203<>""),F203/D203,"")

Sheet 6. Pellet Sales
A1: 6. Pellet Sales
A2: Cash sales of finished pellets to the market
A3: Date | B3: Receipt No. | C3: Customer | D3: Pellets sold (kg) | E3: Unit price ($/kg) | F3: Amount received ($) | G3: Sold by
A4: 2026-07-04 | B4: SR-0001 | C4: Harare Plastics Ltd | D4: 400 | E4: 0.9 | F4: =IF(AND(D4<>"",E4<>""),D4*E4,"") -> 360 | G4: B. Dube
F5: =IF(AND(D5<>"",E5<>""),D5*E5,"")
F6: =IF(AND(D6<>"",E6<>""),D6*E6,"")
F7: =IF(AND(D7<>"",E7<>""),D7*E7,"")
F8: =IF(AND(D8<>"",E8<>""),D8*E8,"")
F9: =IF(AND(D9<>"",E9<>""),D9*E9,"")
F10: =IF(AND(D10<>"",E10<>""),D10*E10,"")
F11: =IF(AND(D11<>"",E11<>""),D11*E11,"")
F12: =IF(AND(D12<>"",E12<>""),D12*E12,"")
F13: =IF(AND(D13<>"",E13<>""),D13*E13,"")
F14: =IF(AND(D14<>"",E14<>""),D14*E14,"")
F15: =IF(AND(D15<>"",E15<>""),D15*E15,"")
F16: =IF(AND(D16<>"",E16<>""),D16*E16,"")
... F203: =IF(AND(D203<>"",E203<>""),D203*E203,"")

Sheet 7. Cash Remittance
A1: 7. Cash Remittance
A2: Cash remitted from Palletizing Office to Crushing Office, capped at kg delivered x recovery price
A3: Date | B3: Voucher No. | C3: Period covered | D3: Chips delivered in period (kg) | E3: Recovery price ($/kg) | F3: Max remittance due ($) | G3: Sales revenue in period ($) | H3: Actual cash remitted ($) | I3: Balance retained by Palletizing Office ($)
A4: 2026-07-05 | B4: CV-0001 | C4: 1-5 Jul 2026 | D4: 465 | E4: 0.5 | F4: =IF(AND(D4<>"",E4<>""),D4*E4,"") -> 232.5 | G4: 360 | H4: 232.5 | I4: =IF(AND(G4<>"",H4<>""),G4-H4,"") -> 127.5
F5: =IF(AND(D5<>"",E5<>""),D5*E5,"") | I5: =IF(AND(G5<>"",H5<>""),G5-H5,"")
F6: =IF(AND(D6<>"",E6<>""),D6*E6,"") | I6: =IF(AND(G6<>"",H6<>""),G6-H6,"")
F7: =IF(AND(D7<>"",E7<>""),D7*E7,"") | I7: =IF(AND(G7<>"",H7<>""),G7-H7,"")
F8: =IF(AND(D8<>"",E8<>""),D8*E8,"") | I8: =IF(AND(G8<>"",H8<>""),G8-H8,"")
F9: =IF(AND(D9<>"",E9<>""),D9*E9,"") | I9: =IF(AND(G9<>"",H9<>""),G9-H9,"")
F10: =IF(AND(D10<>"",E10<>""),D10*E10,"") | I10: =IF(AND(G10<>"",H10<>""),G10-H10,"")
F11: =IF(AND(D11<>"",E11<>""),D11*E11,"") | I11: =IF(AND(G11<>"",H11<>""),G11-H11,"")
F12: =IF(AND(D12<>"",E12<>""),D12*E12,"") | I12: =IF(AND(G12<>"",H12<>""),G12-H12,"")
F13: =IF(AND(D13<>"",E13<>""),D13*E13,"") | I13: =IF(AND(G13<>"",H13<>""),G13-H13,"")
F14: =IF(AND(D14<>"",E14<>""),D14*E14,"") | I14: =IF(AND(G14<>"",H14<>""),G14-H14,"")
F15: =IF(AND(D15<>"",E15<>""),D15*E15,"") | I15: =IF(AND(G15<>"",H15<>""),G15-H15,"")
F16: =IF(AND(D16<>"",E16<>""),D16*E16,"") | I16: =IF(AND(G16<>"",H16<>""),G16-H16,"")
... F203: =IF(AND(D203<>"",E203<>""),D203*E203,"") | I203: =IF(AND(G203<>"",H203<>""),G203-H203,"")
A206: Note: Actual cash remitted should never exceed the Max remittance due (column F). Balance retained = Sales revenue in period − Actual cash remitted.

Sheet Dashboard
A1: Dashboard — Stock & Cash Reconciliation Summary
A2: Updates automatically from the seven log sheets
A4: Crushing Office | D4: Cash reconciliation
A5: Total material purchased (kg) | B5: =SUM('1. Material Intake'!G4:G203) -> 500 | D5: Total sales revenue — pellets ($) | E5: =SUM('6. Pellet Sales'!F4:F203) -> 360
A6: Total value paid to buyers ($) | B6: =SUM('1. Material Intake'!I4:I203) -> 175 | D6: Total amount owed for chips ($) | E6: =B17 -> 46.5
A7: Total input to crusher (kg) | B7: =SUM('2. Crushing Production'!E4:E203) -> 520 | D7: Total cash remitted to Crushing Office ($) | E7: =SUM('7. Cash Remittance'!H4:H203) -> 232.5
A8: Total chips produced (kg) | B8: =SUM('2. Crushing Production'!F4:F203) -> 468 | D8: Outstanding amount owed to Crushing Office ($) | E8: =E6-E7 -> -186
A9: Crushing loss (kg) | B9: =SUM('2. Crushing Production'!G4:G203) -> 52 | D9: Total balance retained by Palletizing Office ($) | E9: =SUM('7. Cash Remittance'!I4:I203) -> 127.5
A10: Crushing loss % | B10: =IF(B7=0,0,B9/B7) -> 0.1 | D10: Check: revenue = remitted + retained | E10: =E5-(E7+E9) -> 0
A11: Total chips dispatched to Palletizing (kg) | B11: =SUM('3. Dispatch to Palletizing'!E4:E203) -> 468
A12: Chips awaiting dispatch — stock on hand (kg) | B12: =B8-B11 -> 0 | D12: "Check" row should read $0.00 once all sales and remittances for a period are logged.
A14: Palletizing Office
A15: Total chips received (kg) | B15: =SUM('4. Palletizing Receipt'!E4:E203) -> 465
A16: Receiving variance vs dispatched (kg) | B16: =B11-B15 -> 3
A17: Total amount payable to Crushing Office ($) | B17: =SUM('4. Palletizing Receipt'!G4:G203) -> 46.5
A18: Total chips input to pelletizing (kg) | B18: =SUM('5. Palletizing Production'!D4:D203) -> 465
A19: Total pellets produced (kg) | B19: =SUM('5. Palletizing Production'!E4:E203) -> 430
A20: Palletizing loss (kg) | B20: =SUM('5. Palletizing Production'!F4:F203) -> 35
A21: Palletizing loss % | B21: =IF(B18=0,0,B20/B18) -> 0.075268817
A22: Total pellets sold (kg) | B22: =SUM('6. Pellet Sales'!D4:D203) -> 400
A23: Finished pellet stock on hand (kg) | B23: =B19-B22 -> 30
